{
  "earthquakes": [
    {
      "latitude": "21.0890000",
      "longitude": "99.9180000",
      "depth": "1.0000",
      "mag": "2.10",
      "magType": "ml",
      "nst": "",
      "gap": "",
      "dmin": "",
      "rms": "",
      "net": "",
      "id": "th_11696_202312311612",
      "updated": "2023-12-31T16:12:18.000Z",
      "location": "Wan Hkang Ho-paw, Shan, Myanmar (Burma)",
      "place": "Myanmar",
      "country": "MM",
      "continent": "Asia",
      "type": "earthquake",
      "timeAdded": "1704041888",
      "timestamp": "1704039138",
      "locationInferred": "1",
      "state": "",
      "initialPosition": "21.09,99.92",
      "time_utc": "2023-12-31 16:12:18",
      "time_mmt": "2023-12-31 22:42:18"
    },
    {
      "latitude": "15.2840000",
      "longitude": "96.1910000",
      "depth": "10.0000",
      "mag": "3.70",
      "magType": "ml",
      "nst": "",
      "gap": "",
      "dmin": "",
      "rms": "",
      "net": "",
      "id": "th_11693_202312300654",
      "updated": "2023-12-30T06:54:38.000Z",
      "location": "",
      "place": "Near South Coast of Myanmar",
      "country": "MM",
      "continent": "Asia",
      "type": "earthquake",
      "timeAdded": "1703926350",
      "timestamp": "1703919278",
      "locationInferred": "0",
      "state": "",
      "initialPosition": "15.28,96.19",
      "time_utc": "2023-12-30 06:54:38",
      "time_mmt": "2023-12-30 13:24:38"
    },
    {
      "latitude": "17.9440000",
      "longitude": "96.4380000",
      "depth": "10.0000",
      "mag": "2.90",
      "magType": "ml",
      "nst": "",
      "gap": "",
      "dmin": "",
      "rms": "",
      "net": "",
      "id": "th_11691_202312300251",
      "updated": "2023-12-30T02:51:49.000Z",
      "location": "Baingda, Bago Region, Myanmar (Burma)",
      "place": "Myanmar",
      "country": "MM",
      "continent": "Asia",
      "type": "earthquake",
      "timeAdded": "1703905537",
      "timestamp": "1703904709",
      "locationInferred": "0",
      "state": "",
      "initialPosition": "17.94,96.44",
      "time_utc": "2023-12-30 02:51:49",
      "time_mmt": "2023-12-30 09:21:49"
    },
    {
      "latitude": "25.1600000",
      "longitude": "96.6100000",
      "depth": "10.0000",
      "mag": "3.50",
      "magType": "ml",
      "nst": "",
      "gap": "",
      "dmin": "",
      "rms": "",
      "net": "",
      "id": "in_MHB0Z2VROGVMclVFQVNTN0dxWUlZQT09",
      "updated": "2023-12-29T17:07:27.000Z",
      "location": "Pinbaw, Kachin, Myanmar (Burma)",
      "place": "Myanmar",
      "country": "MM",
      "continent": "Asia",
      "type": "earthquake",
      "timeAdded": "1703870176",
      "timestamp": "1703869647",
      "locationInferred": "0",
      "state": "",
      "initialPosition": "25.16,96.61",
      "time_utc": "2023-12-29 17:07:27",
      "time_mmt": "2023-12-29 23:37:27"
    },
    {
      "latitude": "25.1829000",
      "longitude": "96.6008000",
      "depth": "10.0000",
      "mag": "5.30",
      "magType": "ml",
      "nst": "",
      "gap": "",
      "dmin": "",
      "rms": "",
      "net": "",
      "id": "in_MnZDNGZ6WW5rMUJueDRLOUU2NXVkQT09",
      "updated": "2023-12-29T22:34:18.000Z",
      "location": "Ywathit, Kachin, Myanmar (Burma)",
      "place": "Myanmar",
      "country": "MM",
      "continent": "Asia",
      "type": "earthquake",
      "timeAdded": "1703867954",
      "timestamp": "1703867477",
      "locationInferred": "1",
      "state": "",
      "initialPosition": "25.14,96.54",
      "time_utc": "2023-12-29 16:31:17",
      "time_mmt": "2023-12-29 23:01:17"
    },
    {
      "latitude": "16.3210000",
      "longitude": "95.9750000",
      "depth": "10.0000",
      "mag": "3.20",
      "magType": "ml",
      "nst": "",
      "gap": "",
      "dmin": "",
      "rms": "",
      "net": "",
      "id": "th_11688_202312282236",
      "updated": "2023-12-28T22:36:57.000Z",
      "location": "Chaunggyi, Ayeyarwady, Myanmar (Burma)",
      "place": "Myanmar",
      "country": "MM",
      "continent": "Asia",
      "type": "earthquake",
      "timeAdded": "1703803934",
      "timestamp": "1703803017",
      "locationInferred": "0",
      "state": "",
      "initialPosition": "16.32,95.98",
      "time_utc": "2023-12-28 22:36:57",
      "time_mmt": "2023-12-29 05:06:57"
    },
    {
      "latitude": "27.4300000",
      "longitude": "97.2100000",
      "depth": "80.0000",
      "mag": "3.50",
      "magType": "ml",
      "nst": "",
      "gap": "",
      "dmin": "",
      "rms": "",
      "net": "",
      "id": "ems_202312_1598684",
      "updated": "2023-12-28T21:14:35.000Z",
      "location": "Hpansak, Kachin, Myanmar (Burma)",
      "place": "Myanmar-india Border Region",
      "country": "MM",
      "continent": "Asia",
      "type": "earthquake",
      "timeAdded": "1703798128",
      "timestamp": "1703794620",
      "locationInferred": "0",
      "state": "",
      "initialPosition": "27.43,97.21",
      "time_utc": "2023-12-28 20:17:00",
      "time_mmt": "2023-12-29 02:47:00"
    },
    {
      "latitude": "18.9830000",
      "longitude": "96.2500000",
      "depth": "10.0000",
      "mag": "2.90",
      "magType": "ml",
      "nst": "",
      "gap": "",
      "dmin": "",
      "rms": "",
      "net": "",
      "id": "th_11685_202312280350",
      "updated": "2023-12-28T03:50:18.000Z",
      "location": "Kyun Kone, Bago Region, Myanmar (Burma)",
      "place": "Myanmar",
      "country": "MM",
      "continent": "Asia",
      "type": "earthquake",
      "timeAdded": "1703736303",
      "timestamp": "1703735418",
      "locationInferred": "0",
      "state": "",
      "initialPosition": "18.98,96.25",
      "time_utc": "2023-12-28 03:50:18",
      "time_mmt": "2023-12-28 10:20:18"
    },
    {
      "latitude": "21.1070000",
      "longitude": "99.4750000",
      "depth": "5.0000",
      "mag": "2.80",
      "magType": "ml",
      "nst": "",
      "gap": "",
      "dmin": "",
      "rms": "",
      "net": "",
      "id": "th_11682_202312261749",
      "updated": "2023-12-26T17:49:36.000Z",
      "location": "Wan Namhing, Shan, Myanmar (Burma)",
      "place": "Myanmar",
      "country": "MM",
      "continent": "Asia",
      "type": "earthquake",
      "timeAdded": "1703614087",
      "timestamp": "1703612976",
      "locationInferred": "0",
      "state": "",
      "initialPosition": "21.11,99.48",
      "time_utc": "2023-12-26 17:49:36",
      "time_mmt": "2023-12-27 00:19:36"
    },
    {
      "latitude": "21.1650000",
      "longitude": "99.3480000",
      "depth": "1.0000",
      "mag": "3.00",
      "magType": "ml",
      "nst": "",
      "gap": "",
      "dmin": "",
      "rms": "",
      "net": "",
      "id": "th_11681_202312260150",
      "updated": "2023-12-26T01:50:06.000Z",
      "location": "Wan Pangkaw, Shan, Myanmar (Burma)",
      "place": "Myanmar",
      "country": "MM",
      "continent": "Asia",
      "type": "earthquake",
      "timeAdded": "1703555732",
      "timestamp": "1703555406",
      "locationInferred": "0",
      "state": "",
      "initialPosition": "21.17,99.35",
      "time_utc": "2023-12-26 01:50:06",
      "time_mmt": "2023-12-26 08:20:06"
    },
    {
      "latitude": "18.2760000",
      "longitude": "95.5800000",
      "depth": "10.0000",
      "mag": "2.90",
      "magType": "ml",
      "nst": "",
      "gap": "",
      "dmin": "",
      "rms": "",
      "net": "",
      "id": "th_11680_202312251517",
      "updated": "2023-12-25T15:17:38.000Z",
      "location": "Zigon, Bago Region, Myanmar (Burma)",
      "place": "Myanmar",
      "country": "MM",
      "continent": "Asia",
      "type": "earthquake",
      "timeAdded": "1703519484",
      "timestamp": "1703517458",
      "locationInferred": "0",
      "state": "",
      "initialPosition": "18.28,95.58",
      "time_utc": "2023-12-25 15:17:38",
      "time_mmt": "2023-12-25 21:47:38"
    },
    {
      "latitude": "21.8700000",
      "longitude": "94.6100000",
      "depth": "75.0000",
      "mag": "3.60",
      "magType": "ml",
      "nst": "",
      "gap": "",
      "dmin": "",
      "rms": "",
      "net": "",
      "id": "in_S3hwZHJFZVpQTmVCSXE3aHpmRHNIZz09",
      "updated": "2023-12-24T04:25:06.000Z",
      "location": "Kaungbwa, Sagaing Region, Myanmar (Burma)",
      "place": "Myanmar",
      "country": "MM",
      "continent": "Asia",
      "type": "earthquake",
      "timeAdded": "1703392468",
      "timestamp": "1703391906",
      "locationInferred": "0",
      "state": "",
      "initialPosition": "21.87,94.61",
      "time_utc": "2023-12-24 04:25:06",
      "time_mmt": "2023-12-24 10:55:06"
    },
    {
      "latitude": "24.3200000",
      "longitude": "94.7000000",
      "depth": "10.0000",
      "mag": "3.10",
      "magType": "ml",
      "nst": "",
      "gap": "",
      "dmin": "",
      "rms": "",
      "net": "",
      "id": "in_dC9SY2N0azdTWUgrQTluM1lCSCtHdz09",
      "updated": "2023-12-23T22:35:35.000Z",
      "location": "Chaunggan, Sagaing Region, Myanmar (Burma)",
      "place": "Myanmar",
      "country": "MM",
      "continent": "Asia",
      "type": "earthquake",
      "timeAdded": "1703370594",
      "timestamp": "1703370060",
      "locationInferred": "0",
      "state": "",
      "initialPosition": "24.32,94.70",
      "time_utc": "2023-12-23 22:21:00",
      "time_mmt": "2023-12-24 04:51:00"
    },
    {
      "latitude": "20.3710000",
      "longitude": "98.2660000",
      "depth": "3.0000",
      "mag": "2.50",
      "magType": "ml",
      "nst": "",
      "gap": "",
      "dmin": "",
      "rms": "",
      "net": "",
      "id": "th_11678_202312231936",
      "updated": "2023-12-23T19:36:28.000Z",
      "location": "Hw\u00e8-hawn, Shan, Myanmar (Burma)",
      "place": "Myanmar",
      "country": "MM",
      "continent": "Asia",
      "type": "earthquake",
      "timeAdded": "1703361852",
      "timestamp": "1703360188",
      "locationInferred": "0",
      "state": "",
      "initialPosition": "20.37,98.27",
      "time_utc": "2023-12-23 19:36:28",
      "time_mmt": "2023-12-24 02:06:28"
    },
    {
      "latitude": "24.7800000",
      "longitude": "94.8000000",
      "depth": "5.0000",
      "mag": "2.70",
      "magType": "ml",
      "nst": "",
      "gap": "",
      "dmin": "",
      "rms": "",
      "net": "",
      "id": "in_dWN0R1ZBbFBMRHhaUENvRW1qSlpzdz09",
      "updated": "2023-12-22T22:07:34.000Z",
      "location": "Gwedaukkon, Sagaing Region, Myanmar (Burma)",
      "place": "Myanmar",
      "country": "MM",
      "continent": "Asia",
      "type": "earthquake",
      "timeAdded": "1703282813",
      "timestamp": "1703282246",
      "locationInferred": "0",
      "state": "",
      "initialPosition": "24.78,94.80",
      "time_utc": "2023-12-22 21:57:26",
      "time_mmt": "2023-12-23 04:27:26"
    },
    {
      "latitude": "20.7960000",
      "longitude": "98.6670000",
      "depth": "5.0000",
      "mag": "2.50",
      "magType": "ml",
      "nst": "",
      "gap": "",
      "dmin": "",
      "rms": "",
      "net": "",
      "id": "th_11673_202312220547",
      "updated": "2023-12-22T05:47:23.000Z",
      "location": "Wan Nawnghkan, Shan, Myanmar (Burma)",
      "place": "Myanmar",
      "country": "MM",
      "continent": "Asia",
      "type": "earthquake",
      "timeAdded": "1703224860",
      "timestamp": "1703224043",
      "locationInferred": "0",
      "state": "",
      "initialPosition": "20.80,98.67",
      "time_utc": "2023-12-22 05:47:23",
      "time_mmt": "2023-12-22 12:17:23"
    },
    {
      "latitude": "21.2440000",
      "longitude": "99.9390000",
      "depth": "1.0000",
      "mag": "2.40",
      "magType": "ml",
      "nst": "",
      "gap": "",
      "dmin": "",
      "rms": "",
      "net": "",
      "id": "th_11672_202312220107",
      "updated": "2023-12-22T01:07:51.000Z",
      "location": "Wan Hkang, Shan, Myanmar (Burma)",
      "place": "Myanmar",
      "country": "MM",
      "continent": "Asia",
      "type": "earthquake",
      "timeAdded": "1703210322",
      "timestamp": "1703207271",
      "locationInferred": "0",
      "state": "",
      "initialPosition": "21.24,99.94",
      "time_utc": "2023-12-22 01:07:51",
      "time_mmt": "2023-12-22 07:37:51"
    },
    {
      "latitude": "18.1227000",
      "longitude": "96.0615000",
      "depth": "10.0000",
      "mag": "4.50",
      "magType": "mb",
      "nst": "32",
      "gap": "154",
      "dmin": "2.758",
      "rms": "0.65",
      "net": "us",
      "id": "ems_202312_1594387",
      "updated": "2023-12-20T15:19:59.040Z",
      "location": "",
      "place": "49km NE of Letpandan, Myanmar",
      "country": "MM",
      "continent": "Asia",
      "type": "earthquake",
      "timeAdded": "1702993623",
      "timestamp": "1702988064",
      "locationInferred": "1",
      "state": "",
      "initialPosition": "18.17,96.10",
      "time_utc": "2023-12-19 12:14:24",
      "time_mmt": "2023-12-19 18:44:24"
    },
    {
      "latitude": "21.1570000",
      "longitude": "99.3340000",
      "depth": "1.0000",
      "mag": "3.20",
      "magType": "ml",
      "nst": "",
      "gap": "",
      "dmin": "",
      "rms": "",
      "net": "",
      "id": "th_11668_202312190908",
      "updated": "2023-12-19T09:08:13.000Z",
      "location": "Wan Pangkaw, Shan, Myanmar (Burma)",
      "place": "Myanmar",
      "country": "MM",
      "continent": "Asia",
      "type": "earthquake",
      "timeAdded": "1702977433",
      "timestamp": "1702976893",
      "locationInferred": "1",
      "state": "",
      "initialPosition": "21.16,99.33",
      "time_utc": "2023-12-19 09:08:13",
      "time_mmt": "2023-12-19 15:38:13"
    },
    {
      "latitude": "22.7300000",
      "longitude": "94.3800000",
      "depth": "116.0000",
      "mag": "3.80",
      "magType": "ml",
      "nst": "",
      "gap": "",
      "dmin": "",
      "rms": "",
      "net": "",
      "id": "in_WmxkbExabVRleGUxang2VHhJb2YxZz09",
      "updated": "2023-12-18T23:43:13.000Z",
      "location": "Tongyi, Sagaing Region, Myanmar (Burma)",
      "place": "Myanmar",
      "country": "MM",
      "continent": "Asia",
      "type": "earthquake",
      "timeAdded": "1702950162",
      "timestamp": "1702942993",
      "locationInferred": "0",
      "state": "",
      "initialPosition": "22.73,94.38",
      "time_utc": "2023-12-18 23:43:13",
      "time_mmt": "2023-12-19 06:13:13"
    },
    {
      "latitude": "21.1130000",
      "longitude": "99.9070000",
      "depth": "1.0000",
      "mag": "1.50",
      "magType": "ml",
      "nst": "",
      "gap": "",
      "dmin": "",
      "rms": "",
      "net": "",
      "id": "th_11662_202312182144",
      "updated": "2023-12-18T21:44:20.000Z",
      "location": "Wan Hsenlong, Shan, Myanmar (Burma)",
      "place": "Myanmar",
      "country": "MM",
      "continent": "Asia",
      "type": "earthquake",
      "timeAdded": "1702936286",
      "timestamp": "1702935860",
      "locationInferred": "1",
      "state": "",
      "initialPosition": "21.11,99.91",
      "time_utc": "2023-12-18 21:44:20",
      "time_mmt": "2023-12-19 04:14:20"
    },
    {
      "latitude": "21.1480000",
      "longitude": "99.9490000",
      "depth": "1.0000",
      "mag": "1.50",
      "magType": "ml",
      "nst": "",
      "gap": "",
      "dmin": "",
      "rms": "",
      "net": "",
      "id": "th_11661_202312181740",
      "updated": "2023-12-18T17:40:03.000Z",
      "location": "Wan Hsenlong, Shan, Myanmar (Burma)",
      "place": "Myanmar",
      "country": "MM",
      "continent": "Asia",
      "type": "earthquake",
      "timeAdded": "1702921490",
      "timestamp": "1702921203",
      "locationInferred": "1",
      "state": "",
      "initialPosition": "21.15,99.95",
      "time_utc": "2023-12-18 17:40:03",
      "time_mmt": "2023-12-19 00:10:03"
    },
    {
      "latitude": "21.1140000",
      "longitude": "99.9650000",
      "depth": "2.0000",
      "mag": "3.40",
      "magType": "ml",
      "nst": "",
      "gap": "",
      "dmin": "",
      "rms": "",
      "net": "",
      "id": "th_11660_202312181701",
      "updated": "2023-12-18T17:01:51.000Z",
      "location": "Wan Hsenlong, Shan, Myanmar (Burma)",
      "place": "Myanmar",
      "country": "MM",
      "continent": "Asia",
      "type": "earthquake",
      "timeAdded": "1702919375",
      "timestamp": "1702918911",
      "locationInferred": "1",
      "state": "",
      "initialPosition": "21.11,99.97",
      "time_utc": "2023-12-18 17:01:51",
      "time_mmt": "2023-12-18 23:31:51"
    },
    {
      "latitude": "21.1590000",
      "longitude": "99.9770000",
      "depth": "2.0000",
      "mag": "2.80",
      "magType": "ml",
      "nst": "",
      "gap": "",
      "dmin": "",
      "rms": "",
      "net": "",
      "id": "th_11658_202312181230",
      "updated": "2023-12-18T12:30:55.000Z",
      "location": "Wan Hsenlong, Shan, Myanmar (Burma)",
      "place": "Myanmar",
      "country": "MM",
      "continent": "Asia",
      "type": "earthquake",
      "timeAdded": "1702904186",
      "timestamp": "1702902655",
      "locationInferred": "1",
      "state": "",
      "initialPosition": "21.16,99.98",
      "time_utc": "2023-12-18 12:30:55",
      "time_mmt": "2023-12-18 19:00:55"
    },
    {
      "latitude": "21.4060000",
      "longitude": "98.4850000",
      "depth": "5.0000",
      "mag": "2.30",
      "magType": "ml",
      "nst": "",
      "gap": "",
      "dmin": "",
      "rms": "",
      "net": "",
      "id": "th_11657_202312180333",
      "updated": "2023-12-18T03:33:41.000Z",
      "location": "Hsaihkao, Shan, Myanmar (Burma)",
      "place": "Myanmar",
      "country": "MM",
      "continent": "Asia",
      "type": "earthquake",
      "timeAdded": "1702873701",
      "timestamp": "1702870421",
      "locationInferred": "0",
      "state": "",
      "initialPosition": "21.41,98.49",
      "time_utc": "2023-12-18 03:33:41",
      "time_mmt": "2023-12-18 10:03:41"
    },
    {
      "latitude": "21.1780000",
      "longitude": "99.9760000",
      "depth": "1.0000",
      "mag": "1.90",
      "magType": "ml",
      "nst": "",
      "gap": "",
      "dmin": "",
      "rms": "",
      "net": "",
      "id": "th_11656_202312180218",
      "updated": "2023-12-18T02:18:56.000Z",
      "location": "Wan Hkang, Shan, Myanmar (Burma)",
      "place": "Myanmar",
      "country": "MM",
      "continent": "Asia",
      "type": "earthquake",
      "timeAdded": "1702870009",
      "timestamp": "1702865936",
      "locationInferred": "1",
      "state": "",
      "initialPosition": "21.18,99.98",
      "time_utc": "2023-12-18 02:18:56",
      "time_mmt": "2023-12-18 08:48:56"
    },
    {
      "latitude": "21.2060000",
      "longitude": "100.0310000",
      "depth": "1.0000",
      "mag": "3.70",
      "magType": "ml",
      "nst": "",
      "gap": "",
      "dmin": "",
      "rms": "",
      "net": "",
      "id": "th_11655_202312172148",
      "updated": "2023-12-17T22:00:37.000Z",
      "location": "Wan Hkang, Shan, Myanmar (Burma)",
      "place": "Myanmar",
      "country": "MM",
      "continent": "Asia",
      "type": "earthquake",
      "timeAdded": "1702850254",
      "timestamp": "1702849703",
      "locationInferred": "0",
      "state": "",
      "initialPosition": "21.21,100.03",
      "time_utc": "2023-12-17 21:48:23",
      "time_mmt": "2023-12-18 04:18:23"
    },
    {
      "latitude": "21.1280000",
      "longitude": "99.3380000",
      "depth": "2.0000",
      "mag": "1.90",
      "magType": "ml",
      "nst": "",
      "gap": "",
      "dmin": "",
      "rms": "",
      "net": "",
      "id": "th_11652_202312162024",
      "updated": "2023-12-16T20:24:49.000Z",
      "location": "Wan Na-hsai, Shan, Myanmar (Burma)",
      "place": "Myanmar",
      "country": "MM",
      "continent": "Asia",
      "type": "earthquake",
      "timeAdded": "1702758854",
      "timestamp": "1702758289",
      "locationInferred": "0",
      "state": "",
      "initialPosition": "21.13,99.34",
      "time_utc": "2023-12-16 20:24:49",
      "time_mmt": "2023-12-17 02:54:49"
    },
    {
      "latitude": "23.2000000",
      "longitude": "94.3000000",
      "depth": "26.0000",
      "mag": "3.60",
      "magType": "ml",
      "nst": "",
      "gap": "",
      "dmin": "",
      "rms": "",
      "net": "",
      "id": "in_WGp0QXh0TU1udEV0SU9LeGExNE1yQT09",
      "updated": "2023-12-16T12:07:34.000Z",
      "location": "Kalewa, Sagaing Region, Myanmar (Burma)",
      "place": "Myanmar",
      "country": "MM",
      "continent": "Asia",
      "type": "earthquake",
      "timeAdded": "1702728301",
      "timestamp": "1702727726",
      "locationInferred": "0",
      "state": "",
      "initialPosition": "23.20,94.30",
      "time_utc": "2023-12-16 11:55:26",
      "time_mmt": "2023-12-16 18:25:26"
    },
    {
      "latitude": "22.8300000",
      "longitude": "94.0700000",
      "depth": "100.0000",
      "mag": "3.20",
      "magType": "ml",
      "nst": "",
      "gap": "",
      "dmin": "",
      "rms": "",
      "net": "",
      "id": "in_bmRaYW1CNFBQUDhqa0hKaTl6SjVoQT09",
      "updated": "2023-12-16T04:07:33.000Z",
      "location": "Tintha, Sagaing Region, Myanmar (Burma)",
      "place": "Myanmar",
      "country": "MM",
      "continent": "Asia",
      "type": "earthquake",
      "timeAdded": "1702699562",
      "timestamp": "1702698599",
      "locationInferred": "0",
      "state": "",
      "initialPosition": "22.83,94.07",
      "time_utc": "2023-12-16 03:49:59",
      "time_mmt": "2023-12-16 10:19:59"
    },
    {
      "latitude": "24.5519000",
      "longitude": "94.7934000",
      "depth": "10.0000",
      "mag": "3.00",
      "magType": "ml",
      "nst": "",
      "gap": "",
      "dmin": "",
      "rms": "",
      "net": "",
      "id": "in_RTNiajV3ME1XRnRHV3YyY2s5emlwZz09",
      "updated": "2023-12-15T20:43:32.000Z",
      "location": "",
      "place": "52km SE of Ukhrul, Manipur, India",
      "country": "MM",
      "continent": "Asia",
      "type": "earthquake",
      "timeAdded": "1702673552",
      "timestamp": "1702673012",
      "locationInferred": "0",
      "state": "",
      "initialPosition": "24.55,94.79",
      "time_utc": "2023-12-15 20:43:32",
      "time_mmt": "2023-12-16 03:13:32"
    },
    {
      "latitude": "21.2620000",
      "longitude": "98.9150000",
      "depth": "2.0000",
      "mag": "3.40",
      "magType": "ml",
      "nst": "",
      "gap": "",
      "dmin": "",
      "rms": "",
      "net": "",
      "id": "th_11650_202312152043",
      "updated": "2023-12-15T20:43:15.000Z",
      "location": "Wan Ho-len, Shan, Myanmar (Burma)",
      "place": "Myanmar",
      "country": "MM",
      "continent": "Asia",
      "type": "earthquake",
      "timeAdded": "1702675439",
      "timestamp": "1702672995",
      "locationInferred": "0",
      "state": "",
      "initialPosition": "21.26,98.92",
      "time_utc": "2023-12-15 20:43:15",
      "time_mmt": "2023-12-16 03:13:15"
    },
    {
      "latitude": "16.2700000",
      "longitude": "95.9100000",
      "depth": "10.0000",
      "mag": "3.80",
      "magType": "ml",
      "nst": "",
      "gap": "",
      "dmin": "",
      "rms": "",
      "net": "",
      "id": "in_RWx2MndqVkozMHJYL1BGczI1VjVTQT09",
      "updated": "2023-12-15T16:30:03.000Z",
      "location": "Ase, Ayeyarwady, Myanmar (Burma)",
      "place": "Myanmar",
      "country": "MM",
      "continent": "Asia",
      "type": "earthquake",
      "timeAdded": "1702658496",
      "timestamp": "1702657803",
      "locationInferred": "0",
      "state": "",
      "initialPosition": "16.27,95.91",
      "time_utc": "2023-12-15 16:30:03",
      "time_mmt": "2023-12-15 23:00:03"
    },
    {
      "latitude": "21.1750000",
      "longitude": "99.3980000",
      "depth": "6.0000",
      "mag": "3.10",
      "magType": "ml",
      "nst": "",
      "gap": "",
      "dmin": "",
      "rms": "",
      "net": "",
      "id": "th_11648_202312151618",
      "updated": "2023-12-15T16:18:56.000Z",
      "location": "Wan Pangkaw, Shan, Myanmar (Burma)",
      "place": "Myanmar",
      "country": "MM",
      "continent": "Asia",
      "type": "earthquake",
      "timeAdded": "1702657870",
      "timestamp": "1702657136",
      "locationInferred": "0",
      "state": "",
      "initialPosition": "21.18,99.40",
      "time_utc": "2023-12-15 16:18:56",
      "time_mmt": "2023-12-15 22:48:56"
    },
    {
      "latitude": "20.4680000",
      "longitude": "99.2250000",
      "depth": "1.0000",
      "mag": "2.20",
      "magType": "ml",
      "nst": "",
      "gap": "",
      "dmin": "",
      "rms": "",
      "net": "",
      "id": "th_11647_202312150114",
      "updated": "2023-12-15T01:14:58.000Z",
      "location": "Mong Hsat, Shan, Myanmar (Burma)",
      "place": "Myanmar",
      "country": "MM",
      "continent": "Asia",
      "type": "earthquake",
      "timeAdded": "1702603690",
      "timestamp": "1702602898",
      "locationInferred": "0",
      "state": "",
      "initialPosition": "20.47,99.23",
      "time_utc": "2023-12-15 01:14:58",
      "time_mmt": "2023-12-15 07:44:58"
    },
    {
      "latitude": "20.3430000",
      "longitude": "99.6670000",
      "depth": "2.0000",
      "mag": "1.50",
      "magType": "ml",
      "nst": "",
      "gap": "",
      "dmin": "",
      "rms": "",
      "net": "",
      "id": "th_11646_202312141621",
      "updated": "2023-12-14T16:21:50.000Z",
      "location": "Wan Ai-hsai, Shan, Myanmar (Burma)",
      "place": "Myanmar",
      "country": "MM",
      "continent": "Asia",
      "type": "earthquake",
      "timeAdded": "1702573049",
      "timestamp": "1702570910",
      "locationInferred": "0",
      "state": "",
      "initialPosition": "20.34,99.67",
      "time_utc": "2023-12-14 16:21:50",
      "time_mmt": "2023-12-14 22:51:50"
    },
    {
      "latitude": "18.0400000",
      "longitude": "96.4180000",
      "depth": "10.0000",
      "mag": "2.70",
      "magType": "ml",
      "nst": "",
      "gap": "",
      "dmin": "",
      "rms": "",
      "net": "",
      "id": "th_11645_202312132319",
      "updated": "2023-12-13T23:19:12.000Z",
      "location": "Myo Chaung, Bago Region, Myanmar (Burma)",
      "place": "Myanmar",
      "country": "MM",
      "continent": "Asia",
      "type": "earthquake",
      "timeAdded": "1702509997",
      "timestamp": "1702509552",
      "locationInferred": "0",
      "state": "",
      "initialPosition": "18.04,96.42",
      "time_utc": "2023-12-13 23:19:12",
      "time_mmt": "2023-12-14 05:49:12"
    },
    {
      "latitude": "24.3200000",
      "longitude": "94.8300000",
      "depth": "120.0000",
      "mag": "3.90",
      "magType": "ml",
      "nst": "",
      "gap": "",
      "dmin": "",
      "rms": "",
      "net": "",
      "id": "in_N2JyWjBSL3AyT1JnRlpDK0U1QmJjQT09",
      "updated": "2023-12-12T20:21:37.000Z",
      "location": "Minya, Sagaing Region, Myanmar (Burma)",
      "place": "Myanmar",
      "country": "MM",
      "continent": "Asia",
      "type": "earthquake",
      "timeAdded": "1702412465",
      "timestamp": "1702411637",
      "locationInferred": "0",
      "state": "",
      "initialPosition": "24.32,94.83",
      "time_utc": "2023-12-12 20:07:17",
      "time_mmt": "2023-12-13 02:37:17"
    },
    {
      "latitude": "21.0780000",
      "longitude": "99.8470000",
      "depth": "1.0000",
      "mag": "1.70",
      "magType": "ml",
      "nst": "",
      "gap": "",
      "dmin": "",
      "rms": "",
      "net": "",
      "id": "th_11643_202312121912",
      "updated": "2023-12-12T19:12:06.000Z",
      "location": "Yangka, Shan, Myanmar (Burma)",
      "place": "Myanmar",
      "country": "MM",
      "continent": "Asia",
      "type": "earthquake",
      "timeAdded": "1702408654",
      "timestamp": "1702408326",
      "locationInferred": "0",
      "state": "",
      "initialPosition": "21.08,99.85",
      "time_utc": "2023-12-12 19:12:06",
      "time_mmt": "2023-12-13 01:42:06"
    },
    {
      "latitude": "21.1580000",
      "longitude": "99.3330000",
      "depth": "4.0000",
      "mag": "1.40",
      "magType": "ml",
      "nst": "",
      "gap": "",
      "dmin": "",
      "rms": "",
      "net": "",
      "id": "th_11642_202312111215",
      "updated": "2023-12-11T12:15:37.000Z",
      "location": "Wan Pangkaw, Shan, Myanmar (Burma)",
      "place": "Myanmar",
      "country": "MM",
      "continent": "Asia",
      "type": "earthquake",
      "timeAdded": "1702298213",
      "timestamp": "1702296937",
      "locationInferred": "1",
      "state": "",
      "initialPosition": "21.16,99.33",
      "time_utc": "2023-12-11 12:15:37",
      "time_mmt": "2023-12-11 18:45:37"
    },
    {
      "latitude": "23.7800000",
      "longitude": "93.8200000",
      "depth": "10.0000",
      "mag": "2.70",
      "magType": "ml",
      "nst": "",
      "gap": "",
      "dmin": "",
      "rms": "",
      "net": "",
      "id": "in_d0dIM1MxQmR5cWtPenE0UkNpRklvQT09",
      "updated": "2023-12-10T10:35:57.000Z",
      "location": "Khuangkhan, Chin State, Myanmar (Burma)",
      "place": "Myanmar",
      "country": "MM",
      "continent": "Asia",
      "type": "earthquake",
      "timeAdded": "1702204000",
      "timestamp": "1702203815",
      "locationInferred": "0",
      "state": "",
      "initialPosition": "23.71,93.85",
      "time_utc": "2023-12-10 10:23:35",
      "time_mmt": "2023-12-10 16:53:35"
    },
    {
      "latitude": "21.1250000",
      "longitude": "99.9000000",
      "depth": "1.0000",
      "mag": "2.10",
      "magType": "ml",
      "nst": "",
      "gap": "",
      "dmin": "",
      "rms": "",
      "net": "",
      "id": "th_11639_202312082148",
      "updated": "2023-12-08T21:48:52.000Z",
      "location": "Wan Hsenlong, Shan, Myanmar (Burma)",
      "place": "Myanmar",
      "country": "MM",
      "continent": "Asia",
      "type": "earthquake",
      "timeAdded": "1702073387",
      "timestamp": "1702072132",
      "locationInferred": "1",
      "state": "",
      "initialPosition": "21.13,99.90",
      "time_utc": "2023-12-08 21:48:52",
      "time_mmt": "2023-12-09 04:18:52"
    },
    {
      "latitude": "24.3500000",
      "longitude": "94.7100000",
      "depth": "10.0000",
      "mag": "3.80",
      "magType": "ml",
      "nst": "",
      "gap": "",
      "dmin": "",
      "rms": "",
      "net": "",
      "id": "in_eHJpSFowdXAxTXduZVN0VXRDWkxoZz09",
      "updated": "2023-12-08T01:14:51.000Z",
      "location": "Chaunggan, Sagaing Region, Myanmar (Burma)",
      "place": "Myanmar",
      "country": "MM",
      "continent": "Asia",
      "type": "earthquake",
      "timeAdded": "1701997900",
      "timestamp": "1701997507",
      "locationInferred": "0",
      "state": "",
      "initialPosition": "24.35,94.71",
      "time_utc": "2023-12-08 01:05:07",
      "time_mmt": "2023-12-08 07:35:07"
    },
    {
      "latitude": "21.1240000",
      "longitude": "99.4760000",
      "depth": "4.0000",
      "mag": "2.80",
      "magType": "ml",
      "nst": "",
      "gap": "",
      "dmin": "",
      "rms": "",
      "net": "",
      "id": "th_11637_202312071300",
      "updated": "2023-12-07T13:00:48.000Z",
      "location": "Wan Namhing, Shan, Myanmar (Burma)",
      "place": "Myanmar",
      "country": "MM",
      "continent": "Asia",
      "type": "earthquake",
      "timeAdded": "1701955584",
      "timestamp": "1701954048",
      "locationInferred": "0",
      "state": "",
      "initialPosition": "21.12,99.48",
      "time_utc": "2023-12-07 13:00:48",
      "time_mmt": "2023-12-07 19:30:48"
    },
    {
      "latitude": "21.0900000",
      "longitude": "99.8810000",
      "depth": "2.0000",
      "mag": "2.60",
      "magType": "ml",
      "nst": "",
      "gap": "",
      "dmin": "",
      "rms": "",
      "net": "",
      "id": "th_11635_202312070049",
      "updated": "2023-12-07T00:49:11.000Z",
      "location": "Yangka, Shan, Myanmar (Burma)",
      "place": "Myanmar",
      "country": "MM",
      "continent": "Asia",
      "type": "earthquake",
      "timeAdded": "1701911227",
      "timestamp": "1701910151",
      "locationInferred": "1",
      "state": "",
      "initialPosition": "21.09,99.88",
      "time_utc": "2023-12-07 00:49:11",
      "time_mmt": "2023-12-07 07:19:11"
    },
    {
      "latitude": "24.6200000",
      "longitude": "95.5900000",
      "depth": "19.0000",
      "mag": "3.30",
      "magType": "ml",
      "nst": "",
      "gap": "",
      "dmin": "",
      "rms": "",
      "net": "",
      "id": "in_WUVVWFh5OUZwZUhFbEdIekFTUG84UT09",
      "updated": "2023-12-06T19:49:56.000Z",
      "location": "Hwemaukkan, Sagaing Region, Myanmar (Burma)",
      "place": "Myanmar",
      "country": "MM",
      "continent": "Asia",
      "type": "earthquake",
      "timeAdded": "1701891810",
      "timestamp": "1701891320",
      "locationInferred": "0",
      "state": "",
      "initialPosition": "24.62,95.59",
      "time_utc": "2023-12-06 19:35:20",
      "time_mmt": "2023-12-07 02:05:20"
    },
    {
      "latitude": "19.5180000",
      "longitude": "96.8280000",
      "depth": "10.0000",
      "mag": "2.70",
      "magType": "ml",
      "nst": "",
      "gap": "",
      "dmin": "",
      "rms": "",
      "net": "",
      "id": "th_11634_202312060345",
      "updated": "2023-12-06T03:45:50.000Z",
      "location": "Kwe Ta Lok",
      "place": "Myanmar",
      "country": "MM",
      "continent": "Asia",
      "type": "earthquake",
      "timeAdded": "1701836992",
      "timestamp": "1701834350",
      "locationInferred": "0",
      "state": "",
      "initialPosition": "19.52,96.83",
      "time_utc": "2023-12-06 03:45:50",
      "time_mmt": "2023-12-06 10:15:50"
    },
    {
      "latitude": "20.3410000",
      "longitude": "98.1320000",
      "depth": "2.0000",
      "mag": "2.60",
      "magType": "ml",
      "nst": "",
      "gap": "",
      "dmin": "",
      "rms": "",
      "net": "",
      "id": "th_11633_202312052137",
      "updated": "2023-12-05T21:37:04.000Z",
      "location": "Wan Hsophwe, Shan, Myanmar (Burma)",
      "place": "Myanmar",
      "country": "MM",
      "continent": "Asia",
      "type": "earthquake",
      "timeAdded": "1701812942",
      "timestamp": "1701812224",
      "locationInferred": "0",
      "state": "",
      "initialPosition": "20.34,98.13",
      "time_utc": "2023-12-05 21:37:04",
      "time_mmt": "2023-12-06 04:07:04"
    },
    {
      "latitude": "19.7990000",
      "longitude": "98.0290000",
      "depth": "10.0000",
      "mag": "1.80",
      "magType": "ml",
      "nst": "",
      "gap": "",
      "dmin": "",
      "rms": "",
      "net": "",
      "id": "th_11631_202312031711",
      "updated": "2023-12-03T17:11:25.000Z",
      "location": "Loikwang, Shan, Myanmar (Burma)",
      "place": "Myanmar",
      "country": "MM",
      "continent": "Asia",
      "type": "earthquake",
      "timeAdded": "1701624694",
      "timestamp": "1701623485",
      "locationInferred": "0",
      "state": "",
      "initialPosition": "19.80,98.03",
      "time_utc": "2023-12-03 17:11:25",
      "time_mmt": "2023-12-03 23:41:25"
    },
    {
      "latitude": "20.4720000",
      "longitude": "98.1510000",
      "depth": "10.0000",
      "mag": "2.50",
      "magType": "ml",
      "nst": "",
      "gap": "",
      "dmin": "",
      "rms": "",
      "net": "",
      "id": "th_11630_202312030730",
      "updated": "2023-12-03T07:30:00.000Z",
      "location": "Hangna, Shan, Myanmar (Burma)",
      "place": "Myanmar",
      "country": "MM",
      "continent": "Asia",
      "type": "earthquake",
      "timeAdded": "1701589345",
      "timestamp": "1701588600",
      "locationInferred": "0",
      "state": "",
      "initialPosition": "20.47,98.15",
      "time_utc": "2023-12-03 07:30:00",
      "time_mmt": "2023-12-03 14:00:00"
    },
    {
      "latitude": "23.5650000",
      "longitude": "98.0540000",
      "depth": "10.0000",
      "mag": "3.90",
      "magType": "ml",
      "nst": "",
      "gap": "",
      "dmin": "",
      "rms": "",
      "net": "",
      "id": "th_11629_202312030715",
      "updated": "2023-12-03T07:15:01.000Z",
      "location": "Tamoenye, Shan, Myanmar (Burma)",
      "place": "Myanmar",
      "country": "MM",
      "continent": "Asia",
      "type": "earthquake",
      "timeAdded": "1701589315",
      "timestamp": "1701587701",
      "locationInferred": "0",
      "state": "",
      "initialPosition": "23.57,98.05",
      "time_utc": "2023-12-03 07:15:01",
      "time_mmt": "2023-12-03 13:45:01"
    },
    {
      "latitude": "23.6270000",
      "longitude": "94.0567000",
      "depth": "66.0000",
      "mag": "4.30",
      "magType": "mb",
      "nst": "",
      "gap": "",
      "dmin": "",
      "rms": "",
      "net": "",
      "id": "ems_202312_1586407",
      "updated": "2023-12-03T15:19:24.000Z",
      "location": "Hpaidin, Chin State, Myanmar (Burma)",
      "place": "Myanmar",
      "country": "MM",
      "continent": "Asia",
      "type": "earthquake",
      "timeAdded": "1701566510",
      "timestamp": "1701566021",
      "locationInferred": "0",
      "state": "",
      "initialPosition": "23.88,93.89",
      "time_utc": "2023-12-03 01:13:41",
      "time_mmt": "2023-12-03 07:43:41"
    }
  ]
}