{
  "earthquakes": [
    {
      "latitude": "19.9800000",
      "longitude": "95.3330000",
      "depth": "117.4000",
      "mag": "4.60",
      "magType": "mb",
      "nst": "45",
      "gap": "82.9",
      "dmin": "",
      "rms": "0.75",
      "net": "us",
      "id": "usp000hv5b",
      "updated": "2014-11-07T01:43:44.638Z",
      "location": "",
      "place": "Myanmar",
      "country": "MM",
      "continent": "Asia",
      "type": "earthquake",
      "timeAdded": "0",
      "timestamp": "0",
      "locationInferred": "1",
      "state": "",
      "initialPosition": "",
      "time_utc": "2011-02-28 00:55:04",
      "time_mmt": "2011-02-28 07:25:04"
    },
    {
      "latitude": "19.5500000",
      "longitude": "95.1240000",
      "depth": "83.6000",
      "mag": "4.70",
      "magType": "mb",
      "nst": "44",
      "gap": "58.7",
      "dmin": "",
      "rms": "0.75",
      "net": "us",
      "id": "usp000hv0y",
      "updated": "2014-11-07T01:43:43.704Z",
      "location": "",
      "place": "Myanmar",
      "country": "MM",
      "continent": "Asia",
      "type": "earthquake",
      "timeAdded": "0",
      "timestamp": "0",
      "locationInferred": "1",
      "state": "",
      "initialPosition": "",
      "time_utc": "2011-02-24 08:28:14",
      "time_mmt": "2011-02-24 14:58:14"
    },
    {
      "latitude": "24.4850000",
      "longitude": "94.7470000",
      "depth": "87.3000",
      "mag": "4.00",
      "magType": "mb",
      "nst": "30",
      "gap": "112.8",
      "dmin": "",
      "rms": "0.54",
      "net": "us",
      "id": "usp000huy9",
      "updated": "2014-11-07T01:43:43.062Z",
      "location": "",
      "place": "Myanmar-India border region",
      "country": "MM",
      "continent": "Asia",
      "type": "earthquake",
      "timeAdded": "0",
      "timestamp": "0",
      "locationInferred": "1",
      "state": "",
      "initialPosition": "",
      "time_utc": "2011-02-22 22:57:27",
      "time_mmt": "2011-02-23 05:27:27"
    },
    {
      "latitude": "26.1140000",
      "longitude": "96.3260000",
      "depth": "59.1000",
      "mag": "4.80",
      "magType": "mb",
      "nst": "99",
      "gap": "59.3",
      "dmin": "",
      "rms": "0.88",
      "net": "us",
      "id": "usp000huhr",
      "updated": "2014-11-07T01:43:40.342Z",
      "location": "",
      "place": "Myanmar",
      "country": "MM",
      "continent": "Asia",
      "type": "earthquake",
      "timeAdded": "0",
      "timestamp": "0",
      "locationInferred": "1",
      "state": "",
      "initialPosition": "",
      "time_utc": "2011-02-14 23:44:33",
      "time_mmt": "2011-02-15 06:14:33"
    },
    {
      "latitude": "22.7520000",
      "longitude": "94.5470000",
      "depth": "100.5000",
      "mag": "4.40",
      "magType": "mb",
      "nst": "46",
      "gap": "57.3",
      "dmin": "",
      "rms": "0.95",
      "net": "us",
      "id": "usp000hufd",
      "updated": "2014-11-07T01:43:39.957Z",
      "location": "",
      "place": "Myanmar",
      "country": "MM",
      "continent": "Asia",
      "type": "earthquake",
      "timeAdded": "0",
      "timestamp": "0",
      "locationInferred": "1",
      "state": "",
      "initialPosition": "",
      "time_utc": "2011-02-13 16:42:10",
      "time_mmt": "2011-02-13 23:12:10"
    },
    {
      "latitude": "24.5310000",
      "longitude": "94.8050000",
      "depth": "78.4000",
      "mag": "4.10",
      "magType": "mb",
      "nst": "11",
      "gap": "112.8",
      "dmin": "",
      "rms": "0.97",
      "net": "us",
      "id": "usp000hu2v",
      "updated": "2014-11-07T01:43:37.280Z",
      "location": "",
      "place": "Myanmar-India border region",
      "country": "MM",
      "continent": "Asia",
      "type": "earthquake",
      "timeAdded": "0",
      "timestamp": "0",
      "locationInferred": "1",
      "state": "",
      "initialPosition": "",
      "time_utc": "2011-02-04 14:06:38",
      "time_mmt": "2011-02-04 20:36:38"
    },
    {
      "latitude": "24.6180000",
      "longitude": "94.6800000",
      "depth": "85.0000",
      "mag": "6.20",
      "magType": "mww",
      "nst": "555",
      "gap": "11.8",
      "dmin": "",
      "rms": "1.04",
      "net": "us",
      "id": "usp000hu2t",
      "updated": "2015-02-12T22:23:49.138Z",
      "location": "",
      "place": "Myanmar-India border region",
      "country": "MM",
      "continent": "Asia",
      "type": "earthquake",
      "timeAdded": "0",
      "timestamp": "0",
      "locationInferred": "1",
      "state": "",
      "initialPosition": "",
      "time_utc": "2011-02-04 13:53:46",
      "time_mmt": "2011-02-04 20:23:46"
    },
    {
      "latitude": "24.6930000",
      "longitude": "97.9430000",
      "depth": "31.1000",
      "mag": "4.80",
      "magType": "mb",
      "nst": "75",
      "gap": "59.8",
      "dmin": "",
      "rms": "1.03",
      "net": "us",
      "id": "usp000htxw",
      "updated": "2014-11-07T01:43:34.333Z",
      "location": "",
      "place": "Myanmar-China border region",
      "country": "MM",
      "continent": "Asia",
      "type": "earthquake",
      "timeAdded": "0",
      "timestamp": "0",
      "locationInferred": "1",
      "state": "",
      "initialPosition": "",
      "time_utc": "2011-02-01 07:11:26",
      "time_mmt": "2011-02-01 13:41:26"
    }
  ]
}