{
  "earthquakes": [
    {
      "latitude": "15.7030000",
      "longitude": "95.9600000",
      "depth": "10.0000",
      "mag": "4.50",
      "magType": "mb",
      "nst": "32",
      "gap": "175.2",
      "dmin": "",
      "rms": "1.1",
      "net": "us",
      "id": "usp000gtap",
      "updated": "2014-11-07T01:38:16.480Z",
      "location": "",
      "place": "near the south coast of Myanmar",
      "country": "MM",
      "continent": "Asia",
      "type": "earthquake",
      "timeAdded": "0",
      "timestamp": "0",
      "locationInferred": "1",
      "state": "",
      "initialPosition": "",
      "time_utc": "2009-01-31 13:56:26",
      "time_mmt": "2009-01-31 20:26:26"
    },
    {
      "latitude": "23.3390000",
      "longitude": "93.9740000",
      "depth": "75.9000",
      "mag": "4.50",
      "magType": "mb",
      "nst": "30",
      "gap": "145.3",
      "dmin": "",
      "rms": "0.71",
      "net": "us",
      "id": "usp000gt8h",
      "updated": "2014-11-07T01:38:16.222Z",
      "location": "",
      "place": "Myanmar-India border region",
      "country": "MM",
      "continent": "Asia",
      "type": "earthquake",
      "timeAdded": "0",
      "timestamp": "0",
      "locationInferred": "1",
      "state": "",
      "initialPosition": "",
      "time_utc": "2009-01-29 22:46:03",
      "time_mmt": "2009-01-30 05:16:03"
    },
    {
      "latitude": "15.6460000",
      "longitude": "96.0380000",
      "depth": "35.0000",
      "mag": "5.00",
      "magType": "mwc",
      "nst": "65",
      "gap": "64.7",
      "dmin": "",
      "rms": "1.26",
      "net": "us",
      "id": "usp000gsxc",
      "updated": "2015-02-11T17:19:02.000Z",
      "location": "",
      "place": "near the south coast of Myanmar",
      "country": "MM",
      "continent": "Asia",
      "type": "earthquake",
      "timeAdded": "0",
      "timestamp": "0",
      "locationInferred": "1",
      "state": "",
      "initialPosition": "",
      "time_utc": "2009-01-21 01:42:24",
      "time_mmt": "2009-01-21 08:12:24"
    },
    {
      "latitude": "19.9830000",
      "longitude": "95.1660000",
      "depth": "109.3000",
      "mag": "4.40",
      "magType": "mb",
      "nst": "42",
      "gap": "170.4",
      "dmin": "",
      "rms": "0.72",
      "net": "us",
      "id": "usp000gsp9",
      "updated": "2014-11-07T01:38:12.633Z",
      "location": "",
      "place": "Myanmar",
      "country": "MM",
      "continent": "Asia",
      "type": "earthquake",
      "timeAdded": "0",
      "timestamp": "0",
      "locationInferred": "1",
      "state": "",
      "initialPosition": "",
      "time_utc": "2009-01-16 09:31:49",
      "time_mmt": "2009-01-16 16:01:49"
    },
    {
      "latitude": "15.6630000",
      "longitude": "96.0150000",
      "depth": "25.0000",
      "mag": "4.60",
      "magType": "mb",
      "nst": "29",
      "gap": "101.3",
      "dmin": "",
      "rms": "1.39",
      "net": "us",
      "id": "usp000gupw",
      "updated": "2014-11-07T01:38:32.973Z",
      "location": "",
      "place": "near the south coast of Myanmar",
      "country": "MM",
      "continent": "Asia",
      "type": "earthquake",
      "timeAdded": "0",
      "timestamp": "0",
      "locationInferred": "1",
      "state": "",
      "initialPosition": "",
      "time_utc": "2009-03-06 14:19:36",
      "time_mmt": "2009-03-06 20:49:36"
    },
    {
      "latitude": "15.5600000",
      "longitude": "96.0600000",
      "depth": "35.0000",
      "mag": "4.50",
      "magType": "mb",
      "nst": "39",
      "gap": "99.5",
      "dmin": "",
      "rms": "0.78",
      "net": "us",
      "id": "usp000gunw",
      "updated": "2014-11-07T01:38:32.693Z",
      "location": "",
      "place": "near the south coast of Myanmar",
      "country": "MM",
      "continent": "Asia",
      "type": "earthquake",
      "timeAdded": "0",
      "timestamp": "0",
      "locationInferred": "1",
      "state": "",
      "initialPosition": "",
      "time_utc": "2009-03-05 20:31:50",
      "time_mmt": "2009-03-06 03:01:50"
    },
    {
      "latitude": "15.5770000",
      "longitude": "95.9930000",
      "depth": "7.9000",
      "mag": "5.10",
      "magType": "mwc",
      "nst": "117",
      "gap": "35.4",
      "dmin": "",
      "rms": "0.94",
      "net": "us",
      "id": "usp000gung",
      "updated": "2015-02-11T17:19:04.000Z",
      "location": "",
      "place": "near the south coast of Myanmar",
      "country": "MM",
      "continent": "Asia",
      "type": "earthquake",
      "timeAdded": "0",
      "timestamp": "0",
      "locationInferred": "1",
      "state": "",
      "initialPosition": "",
      "time_utc": "2009-03-05 15:49:52",
      "time_mmt": "2009-03-05 22:19:52"
    },
    {
      "latitude": "24.8230000",
      "longitude": "95.1790000",
      "depth": "115.5000",
      "mag": "4.70",
      "magType": "mb",
      "nst": "96",
      "gap": "65.8",
      "dmin": "",
      "rms": "0.95",
      "net": "us",
      "id": "usp000gujq",
      "updated": "2014-11-07T01:38:31.607Z",
      "location": "",
      "place": "Myanmar",
      "country": "MM",
      "continent": "Asia",
      "type": "earthquake",
      "timeAdded": "0",
      "timestamp": "0",
      "locationInferred": "1",
      "state": "",
      "initialPosition": "",
      "time_utc": "2009-03-03 01:27:41",
      "time_mmt": "2009-03-03 07:57:41"
    },
    {
      "latitude": "15.7350000",
      "longitude": "96.0130000",
      "depth": "10.0000",
      "mag": "4.30",
      "magType": "mb",
      "nst": "35",
      "gap": "99.5",
      "dmin": "",
      "rms": "1.26",
      "net": "us",
      "id": "usp000guj0",
      "updated": "2014-11-07T01:38:31.366Z",
      "location": "",
      "place": "near the south coast of Myanmar",
      "country": "MM",
      "continent": "Asia",
      "type": "earthquake",
      "timeAdded": "0",
      "timestamp": "0",
      "locationInferred": "1",
      "state": "",
      "initialPosition": "",
      "time_utc": "2009-03-02 12:55:37",
      "time_mmt": "2009-03-02 19:25:37"
    },
    {
      "latitude": "15.6370000",
      "longitude": "95.9400000",
      "depth": "10.0000",
      "mag": "4.60",
      "magType": "mb",
      "nst": "66",
      "gap": "49.7",
      "dmin": "",
      "rms": "1.09",
      "net": "us",
      "id": "usp000guhz",
      "updated": "2014-11-07T01:38:31.351Z",
      "location": "",
      "place": "near the south coast of Myanmar",
      "country": "MM",
      "continent": "Asia",
      "type": "earthquake",
      "timeAdded": "0",
      "timestamp": "0",
      "locationInferred": "1",
      "state": "",
      "initialPosition": "",
      "time_utc": "2009-03-02 12:36:34",
      "time_mmt": "2009-03-02 19:06:34"
    },
    {
      "latitude": "22.9570000",
      "longitude": "94.5350000",
      "depth": "113.5000",
      "mag": "4.30",
      "magType": "mb",
      "nst": "33",
      "gap": "70.7",
      "dmin": "",
      "rms": "0.57",
      "net": "us",
      "id": "usp000gwpm",
      "updated": "2014-11-07T01:38:50.918Z",
      "location": "",
      "place": "Myanmar",
      "country": "MM",
      "continent": "Asia",
      "type": "earthquake",
      "timeAdded": "0",
      "timestamp": "0",
      "locationInferred": "1",
      "state": "",
      "initialPosition": "",
      "time_utc": "2009-04-29 23:31:26",
      "time_mmt": "2009-04-30 06:01:26"
    },
    {
      "latitude": "25.3240000",
      "longitude": "95.0980000",
      "depth": "104.8000",
      "mag": "4.60",
      "magType": "mb",
      "nst": "111",
      "gap": "68.2",
      "dmin": "",
      "rms": "0.67",
      "net": "us",
      "id": "usp000gwa2",
      "updated": "2014-11-07T01:38:47.873Z",
      "location": "",
      "place": "Myanmar",
      "country": "MM",
      "continent": "Asia",
      "type": "earthquake",
      "timeAdded": "0",
      "timestamp": "0",
      "locationInferred": "1",
      "state": "",
      "initialPosition": "",
      "time_utc": "2009-04-17 21:14:25",
      "time_mmt": "2009-04-18 03:44:25"
    },
    {
      "latitude": "25.8360000",
      "longitude": "94.6700000",
      "depth": "33.0000",
      "mag": "4.80",
      "magType": "mb",
      "nst": "74",
      "gap": "66.4",
      "dmin": "",
      "rms": "1.01",
      "net": "us",
      "id": "usp000guc8",
      "updated": "2014-11-07T01:38:26.791Z",
      "location": "",
      "place": "Myanmar-India border region",
      "country": "MM",
      "continent": "Asia",
      "type": "earthquake",
      "timeAdded": "0",
      "timestamp": "0",
      "locationInferred": "1",
      "state": "",
      "initialPosition": "",
      "time_utc": "2009-02-24 17:46:16",
      "time_mmt": "2009-02-25 00:16:16"
    },
    {
      "latitude": "15.6040000",
      "longitude": "96.1710000",
      "depth": "34.3000",
      "mag": "4.30",
      "magType": "mb",
      "nst": "23",
      "gap": "146.1",
      "dmin": "",
      "rms": "0.45",
      "net": "us",
      "id": "usp000gtmd",
      "updated": "2014-11-07T01:38:21.564Z",
      "location": "",
      "place": "near the south coast of Myanmar",
      "country": "MM",
      "continent": "Asia",
      "type": "earthquake",
      "timeAdded": "0",
      "timestamp": "0",
      "locationInferred": "1",
      "state": "",
      "initialPosition": "",
      "time_utc": "2009-02-10 21:56:21",
      "time_mmt": "2009-02-11 04:26:21"
    },
    {
      "latitude": "24.1620000",
      "longitude": "94.6660000",
      "depth": "53.8000",
      "mag": "4.20",
      "magType": "mb",
      "nst": "34",
      "gap": "91.6",
      "dmin": "",
      "rms": "0.85",
      "net": "us",
      "id": "usp000gtgk",
      "updated": "2014-11-07T01:38:20.649Z",
      "location": "",
      "place": "Myanmar-India border region",
      "country": "MM",
      "continent": "Asia",
      "type": "earthquake",
      "timeAdded": "0",
      "timestamp": "0",
      "locationInferred": "1",
      "state": "",
      "initialPosition": "",
      "time_utc": "2009-02-06 07:32:37",
      "time_mmt": "2009-02-06 14:02:37"
    },
    {
      "latitude": "25.2280000",
      "longitude": "96.4630000",
      "depth": "43.8000",
      "mag": "4.20",
      "magType": "mb",
      "nst": "23",
      "gap": "141.3",
      "dmin": "",
      "rms": "1",
      "net": "us",
      "id": "usp000gxa9",
      "updated": "2014-11-07T01:38:59.147Z",
      "location": "",
      "place": "Myanmar",
      "country": "MM",
      "continent": "Asia",
      "type": "earthquake",
      "timeAdded": "0",
      "timestamp": "0",
      "locationInferred": "1",
      "state": "",
      "initialPosition": "",
      "time_utc": "2009-05-19 07:34:59",
      "time_mmt": "2009-05-19 14:04:59"
    },
    {
      "latitude": "24.5770000",
      "longitude": "94.5550000",
      "depth": "74.0000",
      "mag": "4.70",
      "magType": "mb",
      "nst": "83",
      "gap": "67.3",
      "dmin": "",
      "rms": "0.96",
      "net": "us",
      "id": "usp000gx51",
      "updated": "2014-11-07T01:38:57.335Z",
      "location": "",
      "place": "Myanmar-India border region",
      "country": "MM",
      "continent": "Asia",
      "type": "earthquake",
      "timeAdded": "0",
      "timestamp": "0",
      "locationInferred": "1",
      "state": "",
      "initialPosition": "",
      "time_utc": "2009-05-15 15:06:32",
      "time_mmt": "2009-05-15 21:36:32"
    },
    {
      "latitude": "23.5040000",
      "longitude": "94.7260000",
      "depth": "113.0000",
      "mag": "4.70",
      "magType": "mb",
      "nst": "38",
      "gap": "115.4",
      "dmin": "",
      "rms": "0.82",
      "net": "us",
      "id": "usp000gwv4",
      "updated": "2014-11-07T01:38:55.311Z",
      "location": "",
      "place": "Myanmar",
      "country": "MM",
      "continent": "Asia",
      "type": "earthquake",
      "timeAdded": "0",
      "timestamp": "0",
      "locationInferred": "1",
      "state": "",
      "initialPosition": "",
      "time_utc": "2009-05-05 09:23:02",
      "time_mmt": "2009-05-05 15:53:02"
    },
    {
      "latitude": "23.1670000",
      "longitude": "93.8110000",
      "depth": "46.1000",
      "mag": "4.50",
      "magType": "mb",
      "nst": "44",
      "gap": "101.5",
      "dmin": "",
      "rms": "0.97",
      "net": "us",
      "id": "usp000gxu8",
      "updated": "2014-11-07T01:39:06.211Z",
      "location": "",
      "place": "Myanmar-India border region",
      "country": "MM",
      "continent": "Asia",
      "type": "earthquake",
      "timeAdded": "0",
      "timestamp": "0",
      "locationInferred": "1",
      "state": "",
      "initialPosition": "",
      "time_utc": "2009-06-03 19:03:09",
      "time_mmt": "2009-06-04 01:33:09"
    },
    {
      "latitude": "23.3560000",
      "longitude": "93.2100000",
      "depth": "45.3000",
      "mag": "4.30",
      "magType": "mb",
      "nst": "39",
      "gap": "143",
      "dmin": "",
      "rms": "1.28",
      "net": "us",
      "id": "usp000gxu6",
      "updated": "2014-11-07T01:39:06.145Z",
      "location": "",
      "place": "Myanmar-India border region",
      "country": "MM",
      "continent": "Asia",
      "type": "earthquake",
      "timeAdded": "0",
      "timestamp": "0",
      "locationInferred": "1",
      "state": "",
      "initialPosition": "",
      "time_utc": "2009-06-03 18:42:59",
      "time_mmt": "2009-06-04 01:12:59"
    },
    {
      "latitude": "19.8830000",
      "longitude": "93.6190000",
      "depth": "35.0000",
      "mag": "4.10",
      "magType": "mb",
      "nst": "22",
      "gap": "147",
      "dmin": "",
      "rms": "0.78",
      "net": "us",
      "id": "usp000gzhu",
      "updated": "2014-11-07T01:39:20.982Z",
      "location": "",
      "place": "Myanmar",
      "country": "MM",
      "continent": "Asia",
      "type": "earthquake",
      "timeAdded": "0",
      "timestamp": "0",
      "locationInferred": "1",
      "state": "",
      "initialPosition": "",
      "time_utc": "2009-07-22 21:35:47",
      "time_mmt": "2009-07-23 04:05:47"
    },
    {
      "latitude": "22.3720000",
      "longitude": "93.9710000",
      "depth": "30.1000",
      "mag": "4.20",
      "magType": "mb",
      "nst": "22",
      "gap": "104.1",
      "dmin": "",
      "rms": "0.91",
      "net": "us",
      "id": "usp000gz4j",
      "updated": "2014-11-07T01:39:18.749Z",
      "location": "",
      "place": "Myanmar-India border region",
      "country": "MM",
      "continent": "Asia",
      "type": "earthquake",
      "timeAdded": "0",
      "timestamp": "0",
      "locationInferred": "1",
      "state": "",
      "initialPosition": "",
      "time_utc": "2009-07-11 08:52:02",
      "time_mmt": "2009-07-11 15:22:02"
    },
    {
      "latitude": "24.2860000",
      "longitude": "94.1760000",
      "depth": "52.0000",
      "mag": "4.10",
      "magType": "mb",
      "nst": "18",
      "gap": "180.1",
      "dmin": "",
      "rms": "0.86",
      "net": "us",
      "id": "usp000gyzc",
      "updated": "2014-11-07T01:39:17.759Z",
      "location": "",
      "place": "Myanmar-India border region",
      "country": "MM",
      "continent": "Asia",
      "type": "earthquake",
      "timeAdded": "0",
      "timestamp": "0",
      "locationInferred": "1",
      "state": "",
      "initialPosition": "",
      "time_utc": "2009-07-06 09:55:26",
      "time_mmt": "2009-07-06 16:25:26"
    },
    {
      "latitude": "25.2800000",
      "longitude": "95.1010000",
      "depth": "82.2000",
      "mag": "5.30",
      "magType": "mwc",
      "nst": "194",
      "gap": "22.5",
      "dmin": "",
      "rms": "0.96",
      "net": "us",
      "id": "usp000h12d",
      "updated": "2015-02-11T17:19:11.000Z",
      "location": "",
      "place": "Myanmar",
      "country": "MM",
      "continent": "Asia",
      "type": "earthquake",
      "timeAdded": "0",
      "timestamp": "0",
      "locationInferred": "1",
      "state": "",
      "initialPosition": "",
      "time_utc": "2009-08-30 19:27:48",
      "time_mmt": "2009-08-31 01:57:48"
    },
    {
      "latitude": "18.2290000",
      "longitude": "94.1410000",
      "depth": "13.7000",
      "mag": "4.40",
      "magType": "mb",
      "nst": "29",
      "gap": "100.5",
      "dmin": "",
      "rms": "0.58",
      "net": "us",
      "id": "usp000h112",
      "updated": "2014-11-07T01:39:35.101Z",
      "location": "",
      "place": "Myanmar",
      "country": "MM",
      "continent": "Asia",
      "type": "earthquake",
      "timeAdded": "0",
      "timestamp": "0",
      "locationInferred": "1",
      "state": "",
      "initialPosition": "",
      "time_utc": "2009-08-30 02:41:04",
      "time_mmt": "2009-08-30 09:11:04"
    },
    {
      "latitude": "24.3230000",
      "longitude": "94.7930000",
      "depth": "99.0000",
      "mag": "5.50",
      "magType": "mwb",
      "nst": "177",
      "gap": "29.6",
      "dmin": "",
      "rms": "0.8",
      "net": "us",
      "id": "usp000h07g",
      "updated": "2015-02-11T17:19:10.000Z",
      "location": "",
      "place": "Myanmar-India border region",
      "country": "MM",
      "continent": "Asia",
      "type": "earthquake",
      "timeAdded": "0",
      "timestamp": "0",
      "locationInferred": "1",
      "state": "",
      "initialPosition": "",
      "time_utc": "2009-08-11 21:43:47",
      "time_mmt": "2009-08-12 04:13:47"
    },
    {
      "latitude": "22.5130000",
      "longitude": "93.4830000",
      "depth": "72.2000",
      "mag": "4.70",
      "magType": "mb",
      "nst": "83",
      "gap": "71.1",
      "dmin": "",
      "rms": "0.75",
      "net": "us",
      "id": "usp000gzzt",
      "updated": "2014-11-07T01:39:27.811Z",
      "location": "",
      "place": "Myanmar-India border region",
      "country": "MM",
      "continent": "Asia",
      "type": "earthquake",
      "timeAdded": "0",
      "timestamp": "0",
      "locationInferred": "1",
      "state": "",
      "initialPosition": "",
      "time_utc": "2009-08-05 02:58:45",
      "time_mmt": "2009-08-05 09:28:45"
    },
    {
      "latitude": "24.8690000",
      "longitude": "98.0970000",
      "depth": "43.6000",
      "mag": "4.50",
      "magType": "mb",
      "nst": "64",
      "gap": "67.4",
      "dmin": "",
      "rms": "0.52",
      "net": "us",
      "id": "usp000h1um",
      "updated": "2014-11-07T01:39:44.672Z",
      "location": "",
      "place": "Myanmar-China border region",
      "country": "MM",
      "continent": "Asia",
      "type": "earthquake",
      "timeAdded": "0",
      "timestamp": "0",
      "locationInferred": "1",
      "state": "",
      "initialPosition": "",
      "time_utc": "2009-09-25 01:14:17",
      "time_mmt": "2009-09-25 07:44:17"
    },
    {
      "latitude": "20.4040000",
      "longitude": "94.7930000",
      "depth": "84.2000",
      "mag": "5.70",
      "magType": "mwc",
      "nst": "299",
      "gap": "31.7",
      "dmin": "",
      "rms": "0.76",
      "net": "us",
      "id": "usp000h1rn",
      "updated": "2015-02-12T22:59:45.460Z",
      "location": "",
      "place": "Myanmar",
      "country": "MM",
      "continent": "Asia",
      "type": "earthquake",
      "timeAdded": "0",
      "timestamp": "0",
      "locationInferred": "1",
      "state": "",
      "initialPosition": "",
      "time_utc": "2009-09-21 19:38:42",
      "time_mmt": "2009-09-22 02:08:42"
    },
    {
      "latitude": "24.3320000",
      "longitude": "94.6690000",
      "depth": "95.0000",
      "mag": "5.90",
      "magType": "mwc",
      "nst": "358",
      "gap": "14.3",
      "dmin": "",
      "rms": "0.83",
      "net": "us",
      "id": "usp000h16n",
      "updated": "2015-02-12T21:14:02.055Z",
      "location": "",
      "place": "Myanmar-India border region",
      "country": "MM",
      "continent": "Asia",
      "type": "earthquake",
      "timeAdded": "0",
      "timestamp": "0",
      "locationInferred": "1",
      "state": "",
      "initialPosition": "",
      "time_utc": "2009-09-03 19:51:06",
      "time_mmt": "2009-09-04 02:21:06"
    },
    {
      "latitude": "16.8930000",
      "longitude": "95.8170000",
      "depth": "10.0000",
      "mag": "4.20",
      "magType": "mb",
      "nst": "16",
      "gap": "100.7",
      "dmin": "",
      "rms": "0.98",
      "net": "us",
      "id": "usp000h36q",
      "updated": "2014-11-07T01:39:57.392Z",
      "location": "",
      "place": "near the south coast of Myanmar",
      "country": "MM",
      "continent": "Asia",
      "type": "earthquake",
      "timeAdded": "0",
      "timestamp": "0",
      "locationInferred": "1",
      "state": "",
      "initialPosition": "",
      "time_utc": "2009-10-20 08:20:04",
      "time_mmt": "2009-10-20 14:50:04"
    },
    {
      "latitude": "23.2650000",
      "longitude": "94.5030000",
      "depth": "88.4000",
      "mag": "4.80",
      "magType": "mb",
      "nst": "105",
      "gap": "34.6",
      "dmin": "",
      "rms": "0.79",
      "net": "us",
      "id": "usp000h2ru",
      "updated": "2014-11-07T01:39:54.952Z",
      "location": "",
      "place": "Myanmar",
      "country": "MM",
      "continent": "Asia",
      "type": "earthquake",
      "timeAdded": "0",
      "timestamp": "0",
      "locationInferred": "1",
      "state": "",
      "initialPosition": "",
      "time_utc": "2009-10-11 18:26:11",
      "time_mmt": "2009-10-12 00:56:11"
    },
    {
      "latitude": "24.9560000",
      "longitude": "96.4160000",
      "depth": "36.8000",
      "mag": "4.30",
      "magType": "mb",
      "nst": "29",
      "gap": "124.3",
      "dmin": "",
      "rms": "0.98",
      "net": "us",
      "id": "usp000h4eh",
      "updated": "2014-11-07T01:40:08.869Z",
      "location": "",
      "place": "Myanmar",
      "country": "MM",
      "continent": "Asia",
      "type": "earthquake",
      "timeAdded": "0",
      "timestamp": "0",
      "locationInferred": "1",
      "state": "",
      "initialPosition": "",
      "time_utc": "2009-11-26 07:28:52",
      "time_mmt": "2009-11-26 13:58:52"
    },
    {
      "latitude": "24.3570000",
      "longitude": "94.8070000",
      "depth": "124.8000",
      "mag": "5.60",
      "magType": "mwb",
      "nst": "206",
      "gap": "17.3",
      "dmin": "",
      "rms": "0.77",
      "net": "us",
      "id": "usp000h5f4",
      "updated": "2015-02-12T23:40:06.830Z",
      "location": "",
      "place": "Myanmar-India border region",
      "country": "MM",
      "continent": "Asia",
      "type": "earthquake",
      "timeAdded": "0",
      "timestamp": "0",
      "locationInferred": "1",
      "state": "",
      "initialPosition": "",
      "time_utc": "2009-12-29 09:01:55",
      "time_mmt": "2009-12-29 15:31:55"
    },
    {
      "latitude": "23.7290000",
      "longitude": "94.4280000",
      "depth": "74.2000",
      "mag": "4.50",
      "magType": "mb",
      "nst": "46",
      "gap": "95.3",
      "dmin": "",
      "rms": "0.92",
      "net": "us",
      "id": "usp000h564",
      "updated": "2014-11-07T01:40:17.449Z",
      "location": "",
      "place": "Myanmar",
      "country": "MM",
      "continent": "Asia",
      "type": "earthquake",
      "timeAdded": "0",
      "timestamp": "0",
      "locationInferred": "1",
      "state": "",
      "initialPosition": "",
      "time_utc": "2009-12-19 06:18:14",
      "time_mmt": "2009-12-19 12:48:14"
    },
    {
      "latitude": "21.0960000",
      "longitude": "92.5290000",
      "depth": "34.5000",
      "mag": "4.10",
      "magType": "mb",
      "nst": "41",
      "gap": "117.8",
      "dmin": "",
      "rms": "0.68",
      "net": "us",
      "id": "usp000h4yt",
      "updated": "2014-11-07T01:40:15.873Z",
      "location": "",
      "place": "Myanmar-Bangladesh border region",
      "country": "MM",
      "continent": "Asia",
      "type": "earthquake",
      "timeAdded": "0",
      "timestamp": "0",
      "locationInferred": "1",
      "state": "",
      "initialPosition": "",
      "time_utc": "2009-12-11 16:22:17",
      "time_mmt": "2009-12-11 22:52:17"
    },
    {
      "latitude": "23.4810000",
      "longitude": "94.5380000",
      "depth": "35.0000",
      "mag": "4.50",
      "magType": "mb",
      "nst": "38",
      "gap": "96.9",
      "dmin": "",
      "rms": "0.75",
      "net": "us",
      "id": "usp000h4wx",
      "updated": "2014-11-07T01:40:15.458Z",
      "location": "",
      "place": "Myanmar",
      "country": "MM",
      "continent": "Asia",
      "type": "earthquake",
      "timeAdded": "0",
      "timestamp": "0",
      "locationInferred": "1",
      "state": "",
      "initialPosition": "",
      "time_utc": "2009-12-09 21:55:53",
      "time_mmt": "2009-12-10 04:25:53"
    }
  ]
}